{
  "version": "1.0",
  "currentStep": 2,
  "lastUpdated": "2026-02-08T12:30:00.000Z",
  "steps": {
    "0": { "status": "completed", "completedAt": "2026-02-08T12:00:00.000Z" },
    "1": { "status": "completed", "completedAt": "2026-02-08T12:30:00.000Z" },
    "2": { "status": "not-started" },
    "3": { "status": "not-started" },
    "4": { "status": "not-started" },
    "5": { "status": "not-started" },
    "6": { "status": "not-started" },
    "7": { "status": "not-started" },
    "8": { "status": "not-started" },
    "9": { "status": "not-started" },
    "10": { "status": "not-started" },
    "11": { "status": "not-started" },
    "12": { "status": "not-started" },
    "13": { "status": "not-started" },
    "14": { "status": "not-started" },
    "15": { "status": "not-started" },
    "16": { "status": "not-started" },
    "17": { "status": "not-started" }
  },
  "errors": [],
  "filesCreated": [
    "project/vitest.config.ts",
    "project/src/test/setup.ts",
    "project/src/test/sanity.test.ts"
  ]
}
